beatles_chords_markov_chain/__init__.py
beatles_chords_markov_chain/database_preprocessing.py
beatles_chords_markov_chain/intervals.py
beatles_chords_markov_chain/markov_chain.py
beatles_chords_markov_chain/processed_data.py
beatles_chords_markov_chain-0.0.23.dist-info/METADATA
beatles_chords_markov_chain-0.0.23.dist-info/WHEEL
beatles_chords_markov_chain-0.0.23.dist-info/top_level.txt
beatles_chords_markov_chain-0.0.23.dist-info/RECORD
