Metadata-Version: 2.1
Name: beatles-chords-markov-chain
Version: 0.0.23
Summary: A package containing a Markov Chain trained to generate chord progressions.
Home-page: https://https://github.com/FedericoDiMarzo/BeatlesChordsMarkovChain
Author: Federico Di Marzo
Author-email: mail.federicodimarzo@gmail.com
License: UNKNOWN
Project-URL: Bug Tracker, https://https://github.com/FedericoDiMarzo/BeatlesChordsMarkovChain/issues
Platform: UNKNOWN
Classifier: Programming Language :: Python :: 3
Classifier: License :: OSI Approved :: MIT License
Classifier: Operating System :: OS Independent
Requires-Python: >=3.6
Requires-Dist: decorator (==4.4.2)
Requires-Dist: joblib (==1.0.1)
Requires-Dist: melodically (==0.0.8)
Requires-Dist: networkx (==2.5.1)
Requires-Dist: numpy (==1.20.2)
Requires-Dist: pandas (==1.2.4)
Requires-Dist: pomegranate (==0.14.5)
Requires-Dist: python-dateutil (==2.8.1)
Requires-Dist: pytz (==2021.1)
Requires-Dist: PyYAML (==5.4.1)
Requires-Dist: scipy (==1.6.3)
Requires-Dist: six (==1.16.0)
